LICENSE
MANIFEST.in
README.md
setup.py
BluePlug/Base.py
BluePlug/BaseClass.py
BluePlug/FindAxis.py
BluePlug/Init.py
BluePlug/Login.py
BluePlug/MainQuest.py
BluePlug/QtWork.py
BluePlug/SubMom.py
BluePlug/SubTest.py
BluePlug/__init__.py
BluePlug/__version__.py
BluePlug/api.py
BluePlug/core.py
BluePlug/demo_test.py
BluePlug/fork.py
BluePlug/img.py
BluePlug.egg-info/PKG-INFO
BluePlug.egg-info/SOURCES.txt
BluePlug.egg-info/dependency_links.txt
BluePlug.egg-info/top_level.txt